<?xml version="1.0" encoding="UTF-8"?>
<feature
      id="org.topcased.documentimporter"
      label="%featureName"
      version="4.3.0.qualifier"
      provider-name="%providerName">

   <description url="%license">
      %description
   </description>

   <copyright url="%copyrightURL">
      %copyright
   </copyright>

   <license url="%licenseURL">
      %license
   </license>

   <requires>
      <import plugin="org.eclipse.core.runtime"/>
      <import plugin="org.eclipse.emf.ecore"/>
      <import plugin="org.eclipse.emf.edit"/>
      <import plugin="org.eclipse.core.resources"/>
      <import plugin="org.eclipse.emf.ecore.xmi"/>
      <import plugin="org.eclipse.emf.edit.ui"/>
      <import plugin="org.eclipse.ui.ide"/>
      <import plugin="org.eclipse.ui"/>
      <import plugin="org.eclipse.ui.forms"/>
      <import plugin="org.eclipse.emf.common.ui"/>
   </requires>

   <plugin
         id="org.topcased.doc2model.doc2model"
         download-size="0"
         install-size="0"
         version="0.0.0"
         unpack="false"/>

   <plugin
         id="org.topcased.doc2model.doc2model.edit"
         download-size="0"
         install-size="0"
         version="0.0.0"
         unpack="false"/>

   <plugin
         id="org.topcased.doc2model.doc2model.editor"
         download-size="0"
         install-size="0"
         version="0.0.0"
         unpack="false"/>

   <plugin
         id="org.topcased.doc2model.launcher"
         download-size="0"
         install-size="0"
         version="0.0.0"
         unpack="false"/>

   <plugin
         id="org.topcased.doc2model.parser"
         download-size="0"
         install-size="0"
         version="0.0.0"
         unpack="false"/>

   <plugin
         id="org.topcased.document.parser"
         download-size="0"
         install-size="0"
         version="0.0.0"
         unpack="false"/>

</feature>
